jettools/__init__.py
jettools/class_tools.py
jettools/dict_tools.py
jettools/str_tools.py
jettools/validation.py
jettools/version.py
jetts_tools-0.1.0.dist-info/METADATA
jetts_tools-0.1.0.dist-info/WHEEL
jetts_tools-0.1.0.dist-info/top_level.txt
jetts_tools-0.1.0.dist-info/RECORD
